AUTHORS.rst
CONTRIBUTING.rst
HISTORY.rst
LICENSE
MANIFEST.in
README.rst
setup.py
django_forest.egg-info/PKG-INFO
django_forest.egg-info/SOURCES.txt
django_forest.egg-info/dependency_links.txt
django_forest.egg-info/not-zip-safe
django_forest.egg-info/top_level.txt
forest/__init__.py
forest/admin.py
forest/models.py
forest/tests.py
forest/urls.py
forest/views.py
forest/static/forest/js/handlebars.js
forest/static/forest/js/jquery.gridster.js
forest/static/forest/js/jquery.gridster.min.js
forest/templates/forest/base.html
forest/templates/forest/forest.html